{
  "metadata": {
    "source": "Aristotle Political Contributions Database",
    "description": "Sample political contribution records for pay-to-play compliance testing",
    "license": "Licensed data - sample only",
    "last_updated": "2025-01-15",
    "record_count": 25
  },
  "contributions": [
    {
      "id": "CTB-2024-001",
      "contributor_name": "Robert J. Smith",
      "contributor_address": "123 Main Street",
      "contributor_city": "Boston",
      "contributor_state": "MA",
      "contributor_zip": "02108",
      "employer": "Highland Capital Partners",
      "occupation": "Managing Partner",
      "contribution_amount": 400.00,
      "contribution_date": "2024-03-15",
      "recipient_name": "Charlie Baker",
      "recipient_office": "Governor",
      "recipient_state": "MA",
      "election_year": 2024,
      "election_type": "Primary"
    },
    {
      "id": "CTB-2024-002",
      "contributor_name": "Sarah M. Johnson",
      "contributor_address": "456 Oak Avenue",
      "contributor_city": "Cambridge",
      "contributor_state": "MA",
      "contributor_zip": "02139",
      "employer": "Pershing Square Capital",
      "occupation": "Investment Analyst",
      "contribution_amount": 500.00,
      "contribution_date": "2024-02-20",
      "recipient_name": "Maura Healey",
      "recipient_office": "Attorney General",
      "recipient_state": "MA",
      "election_year": 2024,
      "election_type": "General"
    },
    {
      "id": "CTB-2024-003",
      "contributor_name": "Bob Smith",
      "contributor_address": "789 Elm Street",
      "contributor_city": "Brookline",
      "contributor_state": "MA",
      "contributor_zip": "02445",
      "employer": "Self-employed",
      "occupation": "Consultant",
      "contribution_amount": 250.00,
      "contribution_date": "2024-01-10",
      "recipient_name": "Michelle Wu",
      "recipient_office": "Mayor",
      "recipient_state": "MA",
      "election_year": 2024,
      "election_type": "General"
    },
    {
      "id": "CTB-2023-004",
      "contributor_name": "Jennifer L. Williams",
      "contributor_address": "321 Park Drive",
      "contributor_city": "Newton",
      "contributor_state": "MA",
      "contributor_zip": "02458",
      "employer": "Canaan Management LLC",
      "occupation": "Portfolio Manager",
      "contribution_amount": 1000.00,
      "contribution_date": "2023-11-05",
      "recipient_name": "Janet Mills",
      "recipient_office": "Governor",
      "recipient_state": "ME",
      "election_year": 2024,
      "election_type": "General"
    },
    {
      "id": "CTB-2023-005",
      "contributor_name": "Michael Chen",
      "contributor_address": "555 Beacon Street",
      "contributor_city": "Boston",
      "contributor_state": "MA",
      "contributor_zip": "02115",
      "employer": "State Street Corporation",
      "occupation": "Vice President",
      "contribution_amount": 2500.00,
      "contribution_date": "2023-09-12",
      "recipient_name": "Gretchen Whitmer",
      "recipient_office": "Governor",
      "recipient_state": "MI",
      "election_year": 2024,
      "election_type": "General"
    },
    {
      "id": "CTB-2024-006",
      "contributor_name": "Robert Smith Jr",
      "contributor_address": "123 Main St",
      "contributor_city": "Boston",
      "contributor_state": "MA",
      "contributor_zip": "02108",
      "employer": "Highland Capital",
      "occupation": "Partner",
      "contribution_amount": 350.00,
      "contribution_date": "2024-05-20",
      "recipient_name": "Charles Baker",
      "recipient_office": "Governor",
      "recipient_state": "MA",
      "election_year": 2024,
      "election_type": "Primary"
    },
    {
      "id": "CTB-2024-007",
      "contributor_name": "Christopher Anderson",
      "contributor_address": "678 Commonwealth Ave",
      "contributor_city": "Boston",
      "contributor_state": "MA",
      "contributor_zip": "02215",
      "employer": "Goldman Sachs",
      "occupation": "Managing Director",
      "contribution_amount": 5000.00,
      "contribution_date": "2024-01-25",
      "recipient_name": "Andrew Cuomo",
      "recipient_office": "Governor",
      "recipient_state": "NY",
      "election_year": 2024,
      "election_type": "Primary"
    },
    {
      "id": "CTB-2023-008",
      "contributor_name": "Chris Anderson",
      "contributor_address": "678 Commonwealth Avenue",
      "contributor_city": "Boston",
      "contributor_state": "MA",
      "contributor_zip": "02215",
      "employer": "Goldman Sachs & Co",
      "occupation": "MD",
      "contribution_amount": 2500.00,
      "contribution_date": "2023-12-10",
      "recipient_name": "Kathy Hochul",
      "recipient_office": "Governor",
      "recipient_state": "NY",
      "election_year": 2024,
      "election_type": "General"
    },
    {
      "id": "CTB-2024-009",
      "contributor_name": "Elizabeth Martinez",
      "contributor_address": "901 Boylston Street",
      "contributor_city": "Boston",
      "contributor_state": "MA",
      "contributor_zip": "02199",
      "employer": "Bain Capital",
      "occupation": "Senior Associate",
      "contribution_amount": 150.00,
      "contribution_date": "2024-03-08",
      "recipient_name": "Maura Healey",
      "recipient_office": "Governor",
      "recipient_state": "MA",
      "election_year": 2024,
      "election_type": "Primary"
    },
    {
      "id": "CTB-2024-010",
      "contributor_name": "David Lee",
      "contributor_address": "234 Newbury Street",
      "contributor_city": "Boston",
      "contributor_state": "MA",
      "contributor_zip": "02116",
      "employer": "Fidelity Investments",
      "occupation": "Fund Manager",
      "contribution_amount": 400.00,
      "contribution_date": "2024-02-14",
      "recipient_name": "Elizabeth Warren",
      "recipient_office": "US Senator",
      "recipient_state": "MA",
      "election_year": 2024,
      "election_type": "Primary"
    },
    {
      "id": "CTB-2023-011",
      "contributor_name": "Amanda Foster",
      "contributor_address": "567 Marlborough St",
      "contributor_city": "Boston",
      "contributor_state": "MA",
      "contributor_zip": "02115",
      "employer": "Wayzata Investment Partners",
      "occupation": "Principal",
      "contribution_amount": 1500.00,
      "contribution_date": "2023-10-22",
      "recipient_name": "Tim Walz",
      "recipient_office": "Governor",
      "recipient_state": "MN",
      "election_year": 2024,
      "election_type": "General"
    },
    {
      "id": "CTB-2024-012",
      "contributor_name": "James Wilson",
      "contributor_address": "890 Tremont Street",
      "contributor_city": "Boston",
      "contributor_state": "MA",
      "contributor_zip": "02118",
      "employer": "Obra Capital",
      "occupation": "Investment Director",
      "contribution_amount": 7150.00,
      "contribution_date": "2023-08-15",
      "recipient_name": "Gavin Newsom",
      "recipient_office": "Governor",
      "recipient_state": "CA",
      "election_year": 2024,
      "election_type": "Primary"
    },
    {
      "id": "CTB-2024-013",
      "contributor_name": "Maria Garcia",
      "contributor_address": "123 Harvard Avenue",
      "contributor_city": "Allston",
      "contributor_state": "MA",
      "contributor_zip": "02134",
      "employer": "StarVest Partners",
      "occupation": "General Partner",
      "contribution_amount": 1000.00,
      "contribution_date": "2024-01-30",
      "recipient_name": "J.B. Pritzker",
      "recipient_office": "Governor",
      "recipient_state": "IL",
      "election_year": 2024,
      "election_type": "General"
    },
    {
      "id": "CTB-2024-014",
      "contributor_name": "Thomas Brown",
      "contributor_address": "456 Washington Street",
      "contributor_city": "Somerville",
      "contributor_state": "MA",
      "contributor_zip": "02143",
      "employer": "Bank of Hawaii",
      "occupation": "EVP Asset Management",
      "contribution_amount": 2000.00,
      "contribution_date": "2024-04-12",
      "recipient_name": "Josh Green",
      "recipient_office": "Governor",
      "recipient_state": "HI",
      "election_year": 2024,
      "election_type": "Primary"
    },
    {
      "id": "CTB-2023-015",
      "contributor_name": "Lisa Thompson",
      "contributor_address": "789 Broadway",
      "contributor_city": "Cambridge",
      "contributor_state": "MA",
      "contributor_zip": "02142",
      "employer": "Lime Rock Partners",
      "occupation": "Managing Partner",
      "contribution_amount": 5000.00,
      "contribution_date": "2023-07-20",
      "recipient_name": "Roy Cooper",
      "recipient_office": "Governor",
      "recipient_state": "NC",
      "election_year": 2024,
      "election_type": "General"
    },
    {
      "id": "CTB-2024-016",
      "contributor_name": "Robert J Smith",
      "contributor_address": "123 Main Street Apt 4B",
      "contributor_city": "Boston",
      "contributor_state": "MA",
      "contributor_zip": "02108",
      "employer": "Highland Capital Partners LP",
      "occupation": "Managing Partner",
      "contribution_amount": 300.00,
      "contribution_date": "2024-06-01",
      "recipient_name": "Charlie Baker",
      "recipient_office": "Governor",
      "recipient_state": "MA",
      "election_year": 2024,
      "election_type": "General"
    },
    {
      "id": "CTB-2024-017",
      "contributor_name": "Karen White",
      "contributor_address": "234 River Road",
      "contributor_city": "Waltham",
      "contributor_state": "MA",
      "contributor_zip": "02451",
      "employer": "NGN Capital",
      "occupation": "Investment Manager",
      "contribution_amount": 750.00,
      "contribution_date": "2024-02-28",
      "recipient_name": "Ned Lamont",
      "recipient_office": "Governor",
      "recipient_state": "CT",
      "election_year": 2024,
      "election_type": "Primary"
    },
    {
      "id": "CTB-2023-018",
      "contributor_name": "John Davis",
      "contributor_address": "567 Pine Street",
      "contributor_city": "Needham",
      "contributor_state": "MA",
      "contributor_zip": "02492",
      "employer": "Highland Capital Partners",
      "occupation": "Vice President",
      "contribution_amount": 500.00,
      "contribution_date": "2023-11-18",
      "recipient_name": "Charlie Baker",
      "recipient_office": "Governor",
      "recipient_state": "MA",
      "election_year": 2024,
      "election_type": "Primary"
    },
    {
      "id": "CTB-2024-019",
      "contributor_name": "Patricia Miller",
      "contributor_address": "890 Maple Avenue",
      "contributor_city": "Lexington",
      "contributor_state": "MA",
      "contributor_zip": "02420",
      "employer": "State Street Global Advisors",
      "occupation": "Senior Portfolio Manager",
      "contribution_amount": 3000.00,
      "contribution_date": "2024-01-05",
      "recipient_name": "Gretchen Whitmer",
      "recipient_office": "Governor",
      "recipient_state": "MI",
      "election_year": 2024,
      "election_type": "General"
    },
    {
      "id": "CTB-2024-020",
      "contributor_name": "S Johnson",
      "contributor_address": "456 Oak Ave",
      "contributor_city": "Cambridge",
      "contributor_state": "MA",
      "contributor_zip": "02139",
      "employer": "Pershing Square",
      "occupation": "Analyst",
      "contribution_amount": 450.00,
      "contribution_date": "2024-03-22",
      "recipient_name": "M. Healey",
      "recipient_office": "Attorney General",
      "recipient_state": "MA",
      "election_year": 2024,
      "election_type": "General"
    },
    {
      "id": "CTB-2024-021",
      "contributor_name": "William Taylor",
      "contributor_address": "123 Cedar Lane",
      "contributor_city": "Wellesley",
      "contributor_state": "MA",
      "contributor_zip": "02481",
      "employer": "Frazer Lanier Company",
      "occupation": "Partner",
      "contribution_amount": 2000.00,
      "contribution_date": "2024-04-15",
      "recipient_name": "Phil Scott",
      "recipient_office": "Governor",
      "recipient_state": "VT",
      "election_year": 2024,
      "election_type": "Primary"
    },
    {
      "id": "CTB-2023-022",
      "contributor_name": "Susan Rodriguez",
      "contributor_address": "456 Willow Street",
      "contributor_city": "Arlington",
      "contributor_state": "MA",
      "contributor_zip": "02474",
      "employer": "Self-employed",
      "occupation": "Attorney",
      "contribution_amount": 100.00,
      "contribution_date": "2023-12-20",
      "recipient_name": "Maura Healey",
      "recipient_office": "Governor",
      "recipient_state": "MA",
      "election_year": 2024,
      "election_type": "Primary"
    },
    {
      "id": "CTB-2024-023",
      "contributor_name": "Richard Harris",
      "contributor_address": "789 Spring Street",
      "contributor_city": "Medford",
      "contributor_state": "MA",
      "contributor_zip": "02155",
      "employer": "Tufts University Endowment",
      "occupation": "Investment Officer",
      "contribution_amount": 500.00,
      "contribution_date": "2024-05-10",
      "recipient_name": "Maura Healey",
      "recipient_office": "Governor",
      "recipient_state": "MA",
      "election_year": 2024,
      "election_type": "General"
    },
    {
      "id": "CTB-2024-024",
      "contributor_name": "Jennifer Williams",
      "contributor_address": "321 Park Dr Unit 12",
      "contributor_city": "Newton",
      "contributor_state": "MA",
      "contributor_zip": "02458",
      "employer": "Canaan Management",
      "occupation": "Portfolio Mgr",
      "contribution_amount": 1200.00,
      "contribution_date": "2024-02-05",
      "recipient_name": "Janet Mills",
      "recipient_office": "Governor",
      "recipient_state": "ME",
      "election_year": 2024,
      "election_type": "Primary"
    },
    {
      "id": "CTB-2024-025",
      "contributor_name": "Daniel Kim",
      "contributor_address": "567 Lake Drive",
      "contributor_city": "Natick",
      "contributor_state": "MA",
      "contributor_zip": "01760",
      "employer": "MathWorks",
      "occupation": "Software Engineer",
      "contribution_amount": 200.00,
      "contribution_date": "2024-03-30",
      "recipient_name": "Ed Markey",
      "recipient_office": "US Senator",
      "recipient_state": "MA",
      "election_year": 2024,
      "election_type": "Primary"
    }
  ]
}
